gatecode/__init__.py
gatecode/a.py
gatecode/b.py
gatecode/c.py
gatecode/u.py
gatecode-0.0.1.dev0.dist-info/METADATA
gatecode-0.0.1.dev0.dist-info/WHEEL
gatecode-0.0.1.dev0.dist-info/top_level.txt
gatecode-0.0.1.dev0.dist-info/RECORD
