Metadata-Version: 2.1
Name: gatecode
Version: 0.0.1.dev0
Summary: Gate Your Code's Security
Home-page: https://www.gatecode.org
Author: Code Gates
Author-email: admin@gatecode.org
Classifier: Programming Language :: Python :: 3
Classifier: License :: OSI Approved :: MIT License
Classifier: Operating System :: OS Independent
Requires-Python: >=3.6
Requires-Dist: pycryptodome>=3.9.9
